<annotation>
	<folder>ImageSets</folder>
	<filename>Sp_D_CNN_A_art0024_ani0032_0268.jpg</filename>
	<path>C:\virenv\colab\mmdetection\mmdetection_object_detection_demo\data\VOC2007\ImageSets\Sp_D_CNN_A_art0024_ani0032_0268.jpg</path>
	<source>
		<database>Unknown</database>
	</source>
	<size>
		<width>384</width>
		<height>256</height>
		<depth>3</depth>
	</size>
	<segmented>0</segmented>
	<object>
		<name>spliced</name>
		<pose>Unspecified</pose>
		<truncated>0</truncated>
		<difficult>0</difficult>
		<bndbox>
			<xmin>164</xmin>
			<ymin>98</ymin>
			<xmax>278</xmax>
			<ymax>230</ymax>
		</bndbox>
	</object>
</annotation>
